polyglots/__init__.py
polyglots/__main__.py
polyglots-1.0.6.dist-info/LICENSE
polyglots-1.0.6.dist-info/METADATA
polyglots-1.0.6.dist-info/WHEEL
polyglots-1.0.6.dist-info/entry_points.txt
polyglots-1.0.6.dist-info/top_level.txt
polyglots-1.0.6.dist-info/RECORD
