Metadata-Version: 2.1
Name: polyglots
Version: 1.0.6
Summary: Create polyglots for different file types
Home-page: https://github.com/donno2048/polyglots
Author: Elisha Hollander
License: MIT
Platform: UNKNOWN
Classifier: Programming Language :: Python :: 3
License-File: LICENSE
